status_report/__init__.py
status_report/core.py
staus_report-1.0.0.dist-info/LICENSE
staus_report-1.0.0.dist-info/METADATA
staus_report-1.0.0.dist-info/WHEEL
staus_report-1.0.0.dist-info/top_level.txt
staus_report-1.0.0.dist-info/RECORD
