Metadata-Version: 2.1
Name: staus_report
Version: 1.0.0
Summary: status report
Author: Kowalski
Author-email: kowalski33791@gmail.com
Requires-Python: >=3.6
License-File: LICENSE
